MANIFEST.in
README.rst
karotz.py
requirements.txt
setup.py
pykarotz.egg-info/PKG-INFO
pykarotz.egg-info/SOURCES.txt
pykarotz.egg-info/dependency_links.txt
pykarotz.egg-info/entry_points.txt
pykarotz.egg-info/requires.txt
pykarotz.egg-info/top_level.txt
test/test_karotz.py