Metadata-Version: 1.1
Name: pykarotz
Version: 0.2
Summary: karotz python API
Home-page: UNKNOWN
Author: Valentin 'esc' Haenel <valentin.haenel@gmx.de> - Franck Roudet
Author-email: UNKNOWN
License: MIT License
Platform: UNKNOWN
Classifier: Development Status :: 3 - Alpha
Classifier: Topic :: Utilities
Classifier: License :: OSI Approved :: MIT License
